integration_test/__init__.py
integration_test/base.py
integration_test/config.py
integration_test/utils.py
integration_test/ads/__init__.py
integration_test/ads/test_ad_accounts_api.py
integration_test/ads/test_ads_api.py
openapi_generated/__init__.py
openapi_generated/pinterest_client/__init__.py
openapi_generated/pinterest_client/api_client.py
openapi_generated/pinterest_client/configuration.py
openapi_generated/pinterest_client/exceptions.py
openapi_generated/pinterest_client/model_utils.py
openapi_generated/pinterest_client/rest.py
openapi_generated/pinterest_client/api/__init__.py
openapi_generated/pinterest_client/api/ad_accounts_api.py
openapi_generated/pinterest_client/api/ad_groups_api.py
openapi_generated/pinterest_client/api/ads_api.py
openapi_generated/pinterest_client/api/advanced_auction_api.py
openapi_generated/pinterest_client/api/audience_insights_api.py
openapi_generated/pinterest_client/api/audience_sharing_api.py
openapi_generated/pinterest_client/api/audiences_api.py
openapi_generated/pinterest_client/api/billing_api.py
openapi_generated/pinterest_client/api/boards_api.py
openapi_generated/pinterest_client/api/bulk_api.py
openapi_generated/pinterest_client/api/business_access_assets_api.py
openapi_generated/pinterest_client/api/business_access_invite_api.py
openapi_generated/pinterest_client/api/business_access_relationships_api.py
openapi_generated/pinterest_client/api/campaigns_api.py
openapi_generated/pinterest_client/api/catalogs_api.py
openapi_generated/pinterest_client/api/conversion_events_api.py
openapi_generated/pinterest_client/api/conversion_tags_api.py
openapi_generated/pinterest_client/api/customer_lists_api.py
openapi_generated/pinterest_client/api/integrations_api.py
openapi_generated/pinterest_client/api/interests_api.py
openapi_generated/pinterest_client/api/keywords_api.py
openapi_generated/pinterest_client/api/lead_ads_api.py
openapi_generated/pinterest_client/api/lead_forms_api.py
pinterest_generated_client-0.1.11.dist-info/METADATA
pinterest_generated_client-0.1.11.dist-info/WHEEL
pinterest_generated_client-0.1.11.dist-info/top_level.txt
pinterest_generated_client-0.1.11.dist-info/RECORD
