Metadata-Version: 2.4
Name: Pinterest_Generated_Client
Version: 0.1.11
Summary: Pinterest REST API
Home-page: https://github.com/pinterest/pinterest-python-generated-api-client
Author: Pinterest, Inc.
Author-email: pinterest-api@pinterest.com
License: MIT
Keywords: OpenAPI,OpenAPI-Generator,Pinterest REST API
Requires-Dist: urllib3<3,>=1.26
Requires-Dist: python-dateutil
Dynamic: author
Dynamic: author-email
Dynamic: description
Dynamic: description-content-type
Dynamic: home-page
Dynamic: keywords
Dynamic: license
Dynamic: requires-dist
Dynamic: summary
